snaptext/__init__.py
snaptext/core.py
snaptext/json.py
snaptext/string.py
snaptext/value.py
snaptext-0.1.1.dist-info/METADATA
snaptext-0.1.1.dist-info/WHEEL
snaptext-0.1.1.dist-info/top_level.txt
snaptext-0.1.1.dist-info/RECORD
