Metadata-Version: 2.1
Name: snaptext
Version: 0.1.1
Summary: Tools for manipulating strings while retaining source positions in the resulting object
License: EUPL-1.2
Project-URL: repository, https://github.com/slietar/snaptext
Requires-Python: >=3.9
